{
    "mazu": {
        "fishName": "peces",
        "mazuName": "mazu",
        "language": "espa침ol",
        "flags": "游쓇릖,游쀯릖,游뻟릖,游뻟릖",
        "staticStrings": {
            "automateCatchLabel": "automatizar? ",
            "playerNameLabelText": "쯖칩mo se llama? ",
            "fishQuantityLabelText": "쯖u치ntos peces? ",
            "gameCodeTextFieldLabelText": "c칩digo del juego: ",
            "joinGameButton": "unirse",
            "catchButton": "pesque",
            "setNameButton": "Establezca su nombre",
            "loginButton": "ingresar",
            "logoutButton": "cerrar la sesi칩n",
            "tagline": "diosa del mar"
        },
        "attributeNames": {
            "year": "a침o",
            "pop": "pobl",
            "seen": "visto",
            "want": "desea",
            "caught": "conseguido",
            "before": "antes",
            "expenses": "gastos",
            "unitPrice": "precUnit",
            "income": "ingresos",
            "after": "despu칠s",
            "player": "jugador(a)",
            "game": "juego",
            "result": "resultado",
            "level": "nivel"
        },
        "attributeDescriptions": {
            "year": "a침o del juego",
            "pop": "poblaci칩n real al principio del a침o",
            "seen": "cu치ntos peces vio",
            "want": "cuantos peces quer칤a pescar",
            "caught": "cuantos peces pesqu칩",
            "before": "saldo antes del turno",
            "expenses": "gastos de este a침o",
            "unitPrice": "precio unitario",
            "income": "ingresos por la venta de pescado",
            "after": "saldo despu칠s del turno",
            "player": "nombre del jugador(a)",
            "game": "c칩digo del juego",
            "result": "resultado del juego (cu치ntos peces ha conseguido de 5)",
            "level": "nivel de dificultad"
        },
        "mazuFrameTitle": "Mazu, Diosa del Mar",
        "fishFrameTitle": "juego de pesca",
        "sAnd": "y",
        "mazuDatasetTitle": "registros de juego",
        "mazuDatasetDescription": "registros de todos los turnos de los jugadores",
        "fishDataSetTitle": "registros de pesca",
        "fishDataSetDescription": "registros de la experiencia de su barco",
        "fishHistoricalDataSetTitle": "registros hist칩ricos",
        "fishHistoricalDataSetDescription": "registros hist칩ricos de todos los barcos",
        "firstPlayer": "Ser치 el primer jugador",
        "playingSolo": "Est치 jugando solo",
        "oneOtherPlayer": "Hay un jugador m치s",
        "manyOtherPlayers": "Hay %@1 otros jugadores",
        "noPlayersYet": "Todav칤a no hay jugadores",
        "waitingForYou": "Esperando a <strong>Usted</strong>",
        "andHowManyMore": " y %@1 m치s.",
        "waitingFor": "Esperando a",
        "catchFishCommand": "춰Pesque!",
        "end": {
            "timeRanOut": "El juego termina en el a침o %@1.<br>",
            "endedEarly": "El juego termin칩 temprano en %@1. <br>",
            "fiveFishResult": "游游游游游 춰Bien hecho! 춰Cinco peces de cinco! \nLa poblaci칩n total de peces es saludable --- y tan grande que se puede pescar mucho sin reducir la poblaci칩n de peces. La pesca es ahora una fuente sostenible de alimentos.",
            "fourFishResult": "游游游游 Su puntuaci칩n es de cuatro peces (de cinco). <br> 춰El n칰mero total de peces ha aumentado mucho! Ahora puedes capturar m치s peces sin reducir la poblaci칩n. Puedes llegar a las cinco estrellas?",
            "threeFishResult": "游游游 Tu puntuaci칩n es de tres peces (de cinco). <br>El n칰mero total de peces ha aumentado! Tu negocio de pesca va bien, pero podr칤a ir mejor.",
            "twoFishResult": "游游 Tu puntuaci칩n es de dos peces (de cinco). <br>El n칰mero total de peces ha disminuido. Su negocio de pesca ha sobrevivido, pero la poblaci칩n de peces no es saludable.",
            "oneFishResult": "游 Tu puntuaci칩n es s칩lo un pez (de cinco). <br>El n칰mero total de peces es muy bajo. Es posible que no pueda seguir pescando durante mucho tiempo.",
            "zeroFishResult": "游  Su puntuaci칩n es de cero peces (de cinco)! <br> Los peces pronto desaparecer치n y la industria pesquera se ha hundido.",
            "bankruptFishResult": "游  Su puntuaci칩n es de cero peces (de cinco)! <br>Has perdido el juego porque estos jugadores han quebrado: %@1."
        },
        "everyoneHasFished": "Todos han pescado.",
        "waitingForYouToLogIn": "A la espera de que se conecte",
        "waitForFishSale": "Tiene %@1 peces en la pescader칤a. <br>Espere a que se vendan.",
        "noFishWaitForTurnEnd": "No tiene pescado en la pescader칤a. <br>Espere a que termine el turno.",
        "seenFishReport": "Este a침o, Ud ha visto %@1 peces.",
        "caughtAllReport": "<br>Ha cogido el %@1 de peces que quer칤a.",
        "caughtSomeReport": "<br>Quer칤a %@1 de peces, pero pesc칩 solo %@2.",
        "recentTurnReport": "Su 칰ltimo turno completo fue el a침o %@1.<br>Vio %@2 peces, quizo %@3 y pesc %@4.<br>Los vendiste por $%@5 cada uno para un total de $%@6.",
        "buttons": {
            "leaveGameButton": "salir del juego",
            "sellFishButton": "vender pescado",
            "newGameRadioLabel": "nuevo juego",
            "oldGameRadioLabel": "viejo juego"
        },
        "admin": {
            "playerTableHeader": "<tr>\n                <th>nombre</th>\n                <th>desea</th>\n                <th>saldo</th>\n                <th>estado</th>\n                <th>juega</th>\n</tr>",
            "fishMarket": "Pescader칤a",
            "noGameYet": "todav칤a no hay juego",
            "welcomeBack": "Bienvenido de nuevo",
            "welcomeToMazu": "Bienvenido a Mazu",
            "youHaveRejoined": "Ha vuelto a entrar en"
        },
        "timeTerms": {
            "second": "segundos",
            "minute": "minutos",
            "hour": "horas",
            "day": "d칤as",
            "month": "meses"
        }
    }
}